gui/__init__.py
gui/demo.py
gui/ui_main_window.py
tools/__init__.py
ui/__init__.py
ui/demo.py
widget/PaintBoard.py
widget/__init__.py
QEIVideo-0.1a2.dev1.dist-info/METADATA
QEIVideo-0.1a2.dev1.dist-info/WHEEL
QEIVideo-0.1a2.dev1.dist-info/top_level.txt
QEIVideo-0.1a2.dev1.dist-info/RECORD
